Metadata-Version: 1.0
Name: axel-distributions
Version: 0.1
Summary: Gaussian and Binomial distributions
Home-page: UNKNOWN
Author: Axel González
Author-email: axeldasaev@gmail.com
License: UNKNOWN
Platform: UNKNOWN
